console_cowboy/__init__.py
console_cowboy/__main__.py
console_cowboy/cli.py
console_cowboy/validation.py
console_cowboy/ctec/__init__.py
console_cowboy/ctec/schema.py
console_cowboy/ctec/serializers.py
console_cowboy/terminals/__init__.py
console_cowboy/terminals/alacritty.py
console_cowboy/terminals/base.py
console_cowboy/terminals/ghostty.py
console_cowboy/terminals/iterm2.py
console_cowboy/terminals/kitty.py
console_cowboy/terminals/mixins.py
console_cowboy/terminals/terminal_app.py
console_cowboy/terminals/vscode.py
console_cowboy/terminals/hyper/__init__.py
console_cowboy/terminals/hyper/adapter.py
console_cowboy/terminals/hyper/javascript.py
console_cowboy/terminals/wezterm/__init__.py
console_cowboy/terminals/wezterm/adapter.py
console_cowboy/terminals/wezterm/lua.py
console_cowboy/utils/__init__.py
console_cowboy/utils/colors.py
console_cowboy/utils/font_registry.py
console_cowboy/utils/fonts.py
console_cowboy/utils/keycodes.py
console_cowboy/utils/nsarchive.py
console_cowboy-0.6.0.dist-info/licenses/LICENSE
console_cowboy-0.6.0.dist-info/METADATA
console_cowboy-0.6.0.dist-info/WHEEL
console_cowboy-0.6.0.dist-info/entry_points.txt
console_cowboy-0.6.0.dist-info/top_level.txt
console_cowboy-0.6.0.dist-info/RECORD
