Metadata-Version: 2.4
Name: console-cowboy
Version: 0.6.0
Summary: Hop terminals like you hop linux distributions.
Author: zetlen
License-Expression: Apache-2.0
Project-URL: Homepage, https://github.com/zetlen/console-cowboy
Project-URL: Changelog, https://github.com/zetlen/console-cowboy/blob/main/CHANGELOG.md
Project-URL: Issues, https://github.com/zetlen/console-cowboy/issues
Project-URL: CI, https://github.com/zetlen/console-cowboy/actions
Classifier: Development Status :: 4 - Beta
Classifier: Environment :: Console
Classifier: Intended Audience :: Developers
Classifier: Operating System :: OS Independent
Classifier: Programming Language :: Python :: 3
Classifier: Programming Language :: Python :: 3.10
Classifier: Programming Language :: Python :: 3.11
Classifier: Programming Language :: Python :: 3.12
Classifier: Topic :: Utilities
Requires-Python: >=3.10
License-File: LICENSE
Requires-Dist: click
Requires-Dist: dukpy>=0.3
Requires-Dist: lupa>=2.0
Requires-Dist: pyyaml>=6.0
Requires-Dist: tomli>=2.0
Requires-Dist: tomli-w>=1.0
Dynamic: license-file
